gitlab_codecommit_migration/__init__.py
gitlab_codecommit_migration/gitlab_codecommit_migration.py
gitlab_to_codecommit_migration-0.4.0.data/scripts/gitlab-set-read-only
gitlab_to_codecommit_migration-0.4.0.data/scripts/gitlab-to-codecommit
src/gitlab_codecommit_migration/__init__.py
src/gitlab_codecommit_migration/gitlab_codecommit_migration.py
gitlab_to_codecommit_migration-0.4.0.dist-info/LICENSE
gitlab_to_codecommit_migration-0.4.0.dist-info/METADATA
gitlab_to_codecommit_migration-0.4.0.dist-info/WHEEL
gitlab_to_codecommit_migration-0.4.0.dist-info/top_level.txt
gitlab_to_codecommit_migration-0.4.0.dist-info/RECORD
