Metadata-Version: 2.1
Name: gitlab-to-codecommit-migration
Version: 0.4.0
Summary: The sample code provides script to migrate repositories from GitLab to AWS CodeCommit.
Home-page: https://github.com/aws-samples/gitlab-to-codecommit-migration
Author: Martin Schade
Author-email: gitlab-to-codecommit-migration@amazon.com
License: MIT-0 license
Keywords: AWS Codecommit GitLab Migration Move
Platform: UNKNOWN
Classifier: Development Status :: 2 - Pre-Alpha
Classifier: Intended Audience :: Developers
Classifier: License :: OSI Approved :: MIT License
Classifier: Natural Language :: English
Classifier: Programming Language :: Python :: 3.4
Classifier: Programming Language :: Python :: 3.5
Classifier: Programming Language :: Python :: 3.6
Classifier: Programming Language :: Python :: 3.7
Requires-Dist: boto3
Requires-Dist: botocore
Requires-Dist: aws-sam-cli
Requires-Dist: requests
